tabbed/__init__.py
tabbed/py.typed
tabbed/reading.py
tabbed/sniffing.py
tabbed/tabbing.py
tabbed/samples/__init__.py
tabbed/samples/annotations.txt
tabbed/samples/empty.txt
tabbed/samples/raman.txt
tabbed/utils/__init__.py
tabbed/utils/mixins.py
tabbed/utils/parsing.py
tabbed-1.2.0.dist-info/licenses/LICENSE
tabbed-1.2.0.dist-info/METADATA
tabbed-1.2.0.dist-info/WHEEL
tabbed-1.2.0.dist-info/top_level.txt
tabbed-1.2.0.dist-info/RECORD
