Metadata-Version: 2.4
Name: tabbed
Version: 1.2.0
Summary: An iterative reader of irregular text files
Author-email: Matthew Caudill <mscaudill@gmail.com>
License-Expression: BSD-3-Clause
Project-URL: Homepage, https://github.com/mscaudill/tabbed
Keywords: text,delimited,csv,tsv
Classifier: Development Status :: 5 - Production/Stable
Classifier: Operating System :: POSIX :: Linux
Classifier: Programming Language :: Python
Classifier: Programming Language :: Python :: 3
Classifier: Topic :: File Formats
Classifier: Topic :: Text Processing
Classifier: Topic :: Scientific/Engineering
Classifier: Topic :: Scientific/Engineering :: Information Analysis
Requires-Python: >=3.12
License-File: LICENSE
Requires-Dist: clevercsv
Provides-Extra: dev
Requires-Dist: ipython; extra == "dev"
Requires-Dist: pytest; extra == "dev"
Requires-Dist: pytest-cov; extra == "dev"
Requires-Dist: mypy; extra == "dev"
Requires-Dist: pylint; extra == "dev"
Requires-Dist: isort; extra == "dev"
Requires-Dist: codespell; extra == "dev"
Requires-Dist: black; extra == "dev"
Requires-Dist: bumpver; extra == "dev"
Requires-Dist: mkdocs; extra == "dev"
Requires-Dist: mkdocs-material; extra == "dev"
Requires-Dist: mkdocstrings[python]; extra == "dev"
Requires-Dist: mkdocs-jupyter; extra == "dev"
Requires-Dist: pip-tools; extra == "dev"
Requires-Dist: build; extra == "dev"
Requires-Dist: twine; extra == "dev"
Provides-Extra: linting
Requires-Dist: codespell; extra == "linting"
Requires-Dist: isort; extra == "linting"
Requires-Dist: pylint; extra == "linting"
Requires-Dist: black; extra == "linting"
Provides-Extra: typing
Requires-Dist: mypy; extra == "typing"
Provides-Extra: testing
Requires-Dist: pytest; extra == "testing"
Requires-Dist: pytest-cov; extra == "testing"
Dynamic: license-file
